sensation/__init__.py
sensation/common.py
sensation/sen0311/__init__.py
sensation/sen0395/__init__.py
sensation-0.2.1.dist-info/licenses/LICENSE
sensation-0.2.1.dist-info/WHEEL
sensation-0.2.1.dist-info/METADATA
sensation-0.2.1.dist-info/RECORD
