Metadata-Version: 2.4
Name: sensation
Version: 0.2.1
Summary: This is a library for communicating with IoT and home automation sensors and low-level devices.
Author-email: Stan Svec <dev@stansvec.com>
Requires-Python: >=3.11.2
Classifier: License :: OSI Approved :: MIT License
License-File: LICENSE
Requires-Dist: pyserial>=3.5
Requires-Dist: serialio>=2.4.0
Project-URL: Home, https://github.com/symbol-signal/sensation
